aws_jupyter_proxy/__init__.py
aws_jupyter_proxy/awsconfig.py
aws_jupyter_proxy/awsproxy.py
aws_jupyter_proxy/handlers.py
aws_jupyter_proxy/etc/aws_jupyter_proxy.json
tests/__init__.py
tests/unit/__init__.py
tests/unit/test_awsconfig.py
tests/unit/test_awsproxy.py
tests/unit/test_handlers.py
viet_aws_jupyter_proxy-0.3.5.data/data/etc/jupyter/jupyter_notebook_config.d/aws_jupyter_proxy.json
viet_aws_jupyter_proxy-0.3.5.dist-info/LICENSE
viet_aws_jupyter_proxy-0.3.5.dist-info/METADATA
viet_aws_jupyter_proxy-0.3.5.dist-info/NOTICE
viet_aws_jupyter_proxy-0.3.5.dist-info/WHEEL
viet_aws_jupyter_proxy-0.3.5.dist-info/top_level.txt
viet_aws_jupyter_proxy-0.3.5.dist-info/RECORD
