Metadata-Version: 2.1
Name: viet-aws-jupyter-proxy
Version: 0.3.5
Summary: A Jupyter server extension to proxy requests with AWS SigV4 authentication
Home-page: https://github.com/vietle-aws/viet-aws-jupyter-proxy
Author: Amazon Web Services
License: Apache License 2.0
Classifier: Development Status :: 4 - Beta
Requires-Python: >=3.6
License-File: LICENSE
License-File: NOTICE
Requires-Dist: notebook (<7.0,>=6.0)
Requires-Dist: botocore (<2.0,>=1.0)
Provides-Extra: dev
Requires-Dist: asynctest ; extra == 'dev'
Requires-Dist: black ; extra == 'dev'
Requires-Dist: pytest ; extra == 'dev'
Requires-Dist: pytest-asyncio ; extra == 'dev'
Requires-Dist: pytest-cov ; extra == 'dev'
